README.rst
setup.py
dento/__init__.py
dento/main.py
dento.egg-info/PKG-INFO
dento.egg-info/SOURCES.txt
dento.egg-info/dependency_links.txt
dento.egg-info/entry_points.txt
dento.egg-info/requires.txt
dento.egg-info/top_level.txt