Metadata-Version: 1.1
Name: dento
Version: 1.0.0
Summary: dento for stack graphs
Home-page: https://github.com/Denniskamau/stack
Author: Dennis Kamau
Author-email: denniskamau3@gmail.com
License: MIT License
Platform: UNKNOWN
Classifier: Development Status :: 4 - Beta
Classifier: Intended Audience :: Developers
Classifier: Natural Language :: English
Classifier: License :: OSI Approved :: MIT License
Classifier: Programming Language :: Python
Classifier: Programming Language :: Python :: 2.6
Classifier: Programming Language :: Python :: 2.7
Classifier: Programming Language :: Python :: 3
Classifier: Programming Language :: Python :: 3.5
